{"data":{"_id":17000,"properties":{"organization":{"name":"organization","kind":"m:1","cascade":["persist"],"owner":true,"type":"Organization","array":false,"runtimeType":"Organization"},"systemUser":{"name":"systemUser","kind":"m:1","cascade":["persist"],"nullable":true,"owner":true,"type":"SystemUser","array":false,"runtimeType":"SystemUser","optional":true},"clientUser":{"name":"clientUser","kind":"m:1","cascade":["persist"],"nullable":true,"owner":true,"type":"ClientUser","array":false,"runtimeType":"ClientUser","optional":true},"isActive":{"name":"isActive","kind":"scalar","getter":false,"setter":false,"type":"boolean","default":true,"runtimeType":"boolean","array":false}},"primaryKeys":[],"filters":{},"hooks":{},"indexes":[],"uniques":[],"className":"UserOrganization","path":"./src/entities/user-organization.entity.ts","name":"UserOrganization","abstract":false,"internal":true,"constructorParams":[],"toJsonParams":[],"extends":"BaseEntity","useCache":true,"collection":"user_organization"},"origin":"./src/entities/user-organization.entity.ts","hash":"93ab1bd0e3cfa5b43b311dfbddc92464","version":"6.4.1"}
